ffn/__init__.py
ffn/core.py
ffn/data.py
ffn/utils.py
ffn-1.1.1.dist-info/LICENSE
ffn-1.1.1.dist-info/METADATA
ffn-1.1.1.dist-info/WHEEL
ffn-1.1.1.dist-info/top_level.txt
ffn-1.1.1.dist-info/RECORD
