Metadata-Version: 2.1
Name: ffn
Version: 1.1.1
Summary: Financial functions for Python
Author-email: Philippe Morissette <morissette.philippe@gmail.com>
Project-URL: Repository, https://github.com/pmorissette/ffn
Project-URL: Homepage, http://pmorissette.github.io/ffn/
Keywords: python,finance,quant,quant finance,algotrading,algorithmic trading
Classifier: Development Status :: 4 - Beta
Classifier: Programming Language :: Python
Classifier: Programming Language :: Python :: 3
Classifier: Programming Language :: Python :: 3.8
Classifier: Programming Language :: Python :: 3.9
Classifier: Programming Language :: Python :: 3.10
Classifier: Programming Language :: Python :: 3.11
Classifier: Programming Language :: Python :: 3.12
Classifier: Topic :: Software Development :: Libraries
Classifier: License :: OSI Approved :: MIT License
Requires-Python: >=3.8
License-File: LICENSE
Requires-Dist: decorator>=5.0.7
Requires-Dist: matplotlib>=1
Requires-Dist: numpy
Requires-Dist: pandas>=0.19
Requires-Dist: scikit-learn>=0.15
Requires-Dist: scipy>=0.15
Requires-Dist: tabulate>=0.7.5
Requires-Dist: yfinance>=0.2
Provides-Extra: dev
Requires-Dist: build; extra == "dev"
Requires-Dist: ruff<0.8,>=0.5.0; extra == "dev"
Requires-Dist: pytest; extra == "dev"
Requires-Dist: pytest-cov; extra == "dev"
Requires-Dist: setuptools; extra == "dev"
Requires-Dist: twine; extra == "dev"
Requires-Dist: wheel; extra == "dev"
Provides-Extra: test
Requires-Dist: pytest; extra == "test"
Requires-Dist: pytest-cov; extra == "test"
